Metadata-Version: 2.1
Name: Powerbook
Version: 0.1.0
Summary: Generate Powerpoint presentations from a Jupyter Notebook
Home-page: UNKNOWN
Author: Jordan Matelsky
Author-email: opensource@matelsky.com
License: Apache 2.0
Download-URL: https://github.com/j6k4m8/powerbook/tarball/0.1.0
Keywords: powerpoint,jupyter,notebook,reproducibility
Platform: UNKNOWN
Classifier: Development Status :: 4 - Beta
Classifier: Intended Audience :: Developers
Classifier: Programming Language :: Python :: 3.6
Classifier: Programming Language :: Python :: 3.7
Classifier: Programming Language :: Python :: 3.8
Classifier: Programming Language :: Python :: 3.9
